nbkode/__init__.py
nbkode/buffer.py
nbkode/core.py
nbkode/euler.py
nbkode/event_handler.py
nbkode/util.py
nbkode/multistep/adams_bashforth.py
nbkode/multistep/adams_moulton.py
nbkode/multistep/bdf.py
nbkode/multistep/core.py
nbkode/nbcompat/__init__.py
nbkode/nbcompat/common.py
nbkode/nbcompat/nb_to_import.py
nbkode/nbcompat/numbasub.py
nbkode/nbcompat/zeros.py
nbkode/runge_kutta/core.py
nbkode/runge_kutta/diagonally_implicit.py
nbkode/runge_kutta/dop853_coefficients.py
nbkode/runge_kutta/explicit.py
nbkode/runge_kutta/implicit.py
nbkode/runge_kutta/linearly_implicit.py
nbkode/runge_kutta/stabilized_explicit.py
nbkode/testsuite/__init__.py
nbkode/testsuite/test_against_scipy.py
nbkode/testsuite/test_introspection.py
nbkode/testsuite/test_nbcompat.py
nbkode/testsuite/test_solver.py
nbkode/testsuite/test_solver_fs.py
nbkode/testsuite/test_util.py
numbakit_ode-0.5.dist-info/AUTHORS
numbakit_ode-0.5.dist-info/LICENSE
numbakit_ode-0.5.dist-info/METADATA
numbakit_ode-0.5.dist-info/WHEEL
numbakit_ode-0.5.dist-info/top_level.txt
numbakit_ode-0.5.dist-info/zip-safe
numbakit_ode-0.5.dist-info/RECORD
